uzbek_tokenizer/__init__.py
uzbek_tokenizer/segmenter.py
uzbek_tokenizer/data/prefixes.txt
uzbek_tokenizer/data/suffixes.txt
uzbek_tokenizer-0.1.0.dist-info/METADATA
uzbek_tokenizer-0.1.0.dist-info/WHEEL
uzbek_tokenizer-0.1.0.dist-info/top_level.txt
uzbek_tokenizer-0.1.0.dist-info/RECORD
