Metadata-Version: 2.4
Name: uzbek-tokenizer
Version: 0.1.0
Summary: A morphological tokenizer for Uzbek language
Author-email: Ibrat Usmonov <usmonovibrat315@gmail.com>
License: MIT
Project-URL: Homepage, https://github.com/IbratDO/uzbek-tokenizer
Project-URL: Documentation, https://github.com/IbratDO/uzbek-tokenizer#usage
Project-URL: Repository, https://github.com/IbratDO/uzbek-tokenizer.git
Project-URL: Issues, https://github.com/IbratDO/uzbek-tokenizer/issues
Keywords: uzbek,tokenizer,morphology,nlp,segmentation
Classifier: Development Status :: 3 - Alpha
Classifier: Intended Audience :: Developers
Classifier: Intended Audience :: Science/Research
Classifier: License :: OSI Approved :: MIT License
Classifier: Programming Language :: Python :: 3
Classifier: Programming Language :: Python :: 3.8
Classifier: Programming Language :: Python :: 3.9
Classifier: Programming Language :: Python :: 3.10
Classifier: Programming Language :: Python :: 3.11
Classifier: Programming Language :: Python :: 3.12
Classifier: Topic :: Scientific/Engineering
Classifier: Topic :: Text Processing :: Linguistic
Requires-Python: >=3.8
Requires-Dist: regex>=2022.0.0
